brickmos/__about__.py
brickmos/__init__.py
brickmos/brickify.py
brickmos/defaults.py
brickmos-0.1.1.dist-info/METADATA
brickmos-0.1.1.dist-info/WHEEL
brickmos-0.1.1.dist-info/entry_points.txt
brickmos-0.1.1.dist-info/licenses/LICENSE
brickmos-0.1.1.dist-info/RECORD
