Metadata-Version: 2.3
Name: brickmos
Version: 0.1.1
Summary: brickmos is a humble Lego mosaic generator.
Project-URL: Homepage, https://github.com/merschformann/brickmos
Project-URL: Repository, https://github.com/merschformann/brickmos
Author-email: Marius Merschformann <marius.merschformann@gmail.com>
Maintainer-email: Marius Merschformann <marius.merschformann@gmail.com>
License: MIT License
License-File: LICENSE
Keywords: bricklink,lego,mosaic
Classifier: License :: OSI Approved :: MIT License
Classifier: Operating System :: OS Independent
Classifier: Programming Language :: Python :: 3
Requires-Python: >=3.9
Requires-Dist: opencv-python>=4.8.1.78
